shiertier_caption/__init__.py
shiertier_caption/glm4v.py
shiertier_caption/repair_json.py
shiertier_caption/silicon_flow.py
shiertier_caption-0.3.0.dist-info/METADATA
shiertier_caption-0.3.0.dist-info/WHEEL
shiertier_caption-0.3.0.dist-info/top_level.txt
shiertier_caption-0.3.0.dist-info/RECORD
