Metadata-Version: 2.2
Name: shiertier_caption
Version: 0.3.0
Summary: 一个使用智谱AI GLM4V-Plus模型进行图片描述的Python包
Author-email: shiertier <junjietext@gmail.com>
Project-URL: Homepage, https://github.com/shiertier_utils/shiertier_caption
Project-URL: Documentation, https://github.com/shiertier_utils/shiertier_caption#readme
Project-URL: Repository, https://github.com/shiertier_utils/shiertier_caption.git
Project-URL: Issues, https://github.com/shiertier_utils/shiertier_caption/issues
Keywords: zhipuai,glm4v,shiertier_caption,image,ai
Classifier: License :: OSI Approved :: MIT License
Classifier: Programming Language :: Python
Classifier: Programming Language :: Python :: 3
Classifier: Programming Language :: Python :: 3.7
Classifier: Programming Language :: Python :: 3.8
Classifier: Programming Language :: Python :: 3.9
Classifier: Programming Language :: Python :: 3.10
Classifier: Programming Language :: Python :: 3.11
Requires-Python: >=3.7
Requires-Dist: zhipuai>=1.0.0
Requires-Dist: json_repair
Requires-Dist: typed-ast
Requires-Dist: tqdm
Requires-Dist: hfpics
Provides-Extra: dev
Requires-Dist: pytest>=6.0; extra == "dev"
Requires-Dist: pytest-cov>=2.0; extra == "dev"
Requires-Dist: black>=22.0; extra == "dev"
Requires-Dist: isort>=5.0; extra == "dev"
Requires-Dist: mypy>=0.900; extra == "dev"
Requires-Dist: build>=0.7.0; extra == "dev"
Requires-Dist: twine>=3.4.0; extra == "dev"
